msl/kcdb/__about__.py
msl/kcdb/__init__.py
msl/kcdb/_version.py
msl/kcdb/chemistry_biology.py
msl/kcdb/general_physics.py
msl/kcdb/ionizing_radiation.py
msl/kcdb/kcdb.py
msl/kcdb/py.typed
msl/kcdb/types.py
msl_kcdb-1.0.0.dist-info/METADATA
msl_kcdb-1.0.0.dist-info/WHEEL
msl_kcdb-1.0.0.dist-info/licenses/LICENSE.txt
msl_kcdb-1.0.0.dist-info/RECORD
