Metadata-Version: 2.4
Name: msl-kcdb
Version: 1.0.0
Summary: Search the BIPM key comparison database (KCDB).
Project-URL: Changelog, https://mslnz.github.io/msl-kcdb/about/release-notes/
Project-URL: Documentation, https://mslnz.github.io/msl-kcdb/
Project-URL: Homepage, https://mslnz.github.io/msl-kcdb/
Project-URL: Issues, https://github.com/MSLNZ/msl-kcdb/issues
Project-URL: Source, https://github.com/MSLNZ/msl-kcdb
Author-email: Measurement Standards Laboratory of New Zealand <info@measurement.govt.nz>
Maintainer-email: Joseph Borbely <joseph.borbely@measurement.govt.nz>
License: MIT License
License-File: LICENSE.txt
Keywords: API,BIPM,KCDB,MSL
Classifier: Development Status :: 4 - Beta
Classifier: Intended Audience :: Developers
Classifier: Intended Audience :: Science/Research
Classifier: License :: OSI Approved :: MIT License
Classifier: Operating System :: OS Independent
Classifier: Programming Language :: Python
Classifier: Programming Language :: Python :: 3
Classifier: Programming Language :: Python :: 3.8
Classifier: Programming Language :: Python :: 3.9
Classifier: Programming Language :: Python :: 3.10
Classifier: Programming Language :: Python :: 3.11
Classifier: Programming Language :: Python :: 3.12
Classifier: Programming Language :: Python :: 3.13
Classifier: Topic :: Scientific/Engineering
Classifier: Topic :: Software Development
Requires-Python: >=3.8
